llamapy/__init__.py
llamapy/llamapy.py
tests/__init__.py
tests/test_llamapy.py
llamapy_clapham13-0.0.1.dist-info/LICENSE
llamapy_clapham13-0.0.1.dist-info/METADATA
llamapy_clapham13-0.0.1.dist-info/WHEEL
llamapy_clapham13-0.0.1.dist-info/top_level.txt
llamapy_clapham13-0.0.1.dist-info/RECORD
