Metadata-Version: 2.1
Name: llamapy-clapham13
Version: 0.0.1
Summary: A package to make interfacing between Airpy and Google Sheets easier
Home-page: https://github.com/clapham13/llamapy
Author: Alex Shannon
Author-email: alex.shannon@airbnb.com
License: UNKNOWN
Platform: UNKNOWN
Classifier: Programming Language :: Python :: 3
Classifier: License :: OSI Approved :: MIT License
Classifier: Operating System :: OS Independent
Requires-Python: >=3.6
